turboalias/__init__.py
turboalias/cli.py
turboalias/config.py
turboalias/datastructures.py
turboalias/shell.py
turboalias/sync.py
turboalias/default_aliases.json
turboalias-0.0.5.dist-info/METADATA
turboalias-0.0.5.dist-info/WHEEL
turboalias-0.0.5.dist-info/entry_points.txt
turboalias-0.0.5.dist-info/licenses/LICENSE
turboalias-0.0.5.dist-info/RECORD
