Metadata-Version: 2.4
Name: turboalias
Version: 0.0.5
Summary: Cross-workstation alias manager for bash and zsh
Project-URL: Homepage, https://github.com/mcdominik/turboalias
Project-URL: Bug Tracker, https://github.com/mcdominik/turboalias/issues
Author-email: Dominik Mackiewicz <ddominik.mackiewicz@gmail.com>
License-Expression: MIT
License-File: LICENSE
Keywords: alias,aliases,bash,shell,terminal,zsh
Classifier: Operating System :: OS Independent
Classifier: Programming Language :: Python :: 3
Requires-Python: >=3.9
